commode_utils/__init__.py
commode_utils/common.py
commode_utils/filesystem.py
commode_utils/py.typed
commode_utils/training.py
commode_utils/vocabulary.py
commode_utils/callbacks/__init__.py
commode_utils/callbacks/model_checkpoint_with_upload_callback.py
commode_utils/callbacks/print_epoch_result_callback.py
commode_utils/losses/__init__.py
commode_utils/losses/sequence_cross_entropy.py
commode_utils/metrics/__init__.py
commode_utils/metrics/chrF.py
commode_utils/metrics/classification.py
commode_utils/metrics/sequential_f1.py
commode_utils/modules/__init__.py
commode_utils/modules/attention.py
commode_utils/modules/base_decoder_step.py
commode_utils/modules/classifier.py
commode_utils/modules/decoder.py
commode_utils/modules/lstm_decoder_step.py
commode_utils-0.4.2.dist-info/LICENSE
commode_utils-0.4.2.dist-info/METADATA
commode_utils-0.4.2.dist-info/WHEEL
commode_utils-0.4.2.dist-info/top_level.txt
commode_utils-0.4.2.dist-info/RECORD
