Metadata-Version: 2.1
Name: commode-utils
Version: 0.4.2
Summary: Set of useful functions and modules for Code Modeling
Home-page: https://github.com/SpirinEgor/commode-utils
Author: Egor Spirin
Author-email: spirin.egor@gmail.com
License: Apache 2.0
Download-URL: https://pypi.org/project/commode-utils/
Platform: UNKNOWN
License-File: LICENSE
Requires-Dist: tqdm (>=4.62.0)
Requires-Dist: torchmetrics (>=0.6.0)
Requires-Dist: torch (>=1.10.0)
Requires-Dist: omegaconf (>=2.1.0)
Requires-Dist: pytorch-lightning (>=1.5.0)
Requires-Dist: sacrebleu (>=2.0.0)
